swefficiency/__init__.py
swefficiency/cli.py
swefficiency/report.py
swefficiency/collect/__init__.py
swefficiency/collect/build_dataset.py
swefficiency/collect/get_tasks_pipeline.py
swefficiency/collect/print_pulls.py
swefficiency/collect/utils.py
swefficiency/harness/__init__.py
swefficiency/harness/_coverage_analysis.py
swefficiency/harness/_coverage_analysis2.py
swefficiency/harness/_coverage_ast.py
swefficiency/harness/_introspection_patch_check.py
swefficiency/harness/_meaningful_edit.py
swefficiency/harness/constants.py
swefficiency/harness/cpu_assignment.py
swefficiency/harness/docker_build.py
swefficiency/harness/docker_utils.py
swefficiency/harness/dockerfiles.py
swefficiency/harness/grading.py
swefficiency/harness/log_parsers.py
swefficiency/harness/run_evaluation.py
swefficiency/harness/run_to_run_isolation.py
swefficiency/harness/run_validation.py
swefficiency/harness/test_spec.py
swefficiency/harness/utils.py
swefficiency/perf_filter/utils.py
swefficiency/perf_filter/attributes/constants.py
swefficiency/perf_filter/attributes/filter.py
swefficiency/versioning/__init__.py
swefficiency/versioning/constants.py
swefficiency/versioning/get_versions.py
swefficiency/versioning/utils.py
swefficiency/versioning/extract_web/get_versions_astropy.py
swefficiency/versioning/extract_web/get_versions_dask.py
swefficiency/versioning/extract_web/get_versions_matplotlib.py
swefficiency/versioning/extract_web/get_versions_modin.py
swefficiency/versioning/extract_web/get_versions_numpy.py
swefficiency/versioning/extract_web/get_versions_pandas.py
swefficiency/versioning/extract_web/get_versions_pvlib-python.py
swefficiency/versioning/extract_web/get_versions_pydicom.py
swefficiency/versioning/extract_web/get_versions_pytensor.py
swefficiency/versioning/extract_web/get_versions_scipy.py
swefficiency/versioning/extract_web/get_versions_scipy_test.py
swefficiency/versioning/extract_web/get_versions_sqlfluff.py
swefficiency/versioning/extract_web/get_versions_statsmodels.py
swefficiency-1.0.0.dist-info/licenses/LICENSE
swefficiency-1.0.0.dist-info/METADATA
swefficiency-1.0.0.dist-info/WHEEL
swefficiency-1.0.0.dist-info/entry_points.txt
swefficiency-1.0.0.dist-info/top_level.txt
swefficiency-1.0.0.dist-info/RECORD
