Metadata-Version: 2.4
Name: swefficiency
Version: 1.0.0
Summary: The official SWE-fficiency package - a benchmark for evaluating LMs on automated performance engineering
Author-email: SWEfficiency Team <swefficiencyperf@gmail.com>
License: Apache-2.0
Project-URL: Homepage, https://swefficiency.com
Project-URL: Repository, https://github.com/swefficiency/swefficiency
Project-URL: Documentation, https://github.com/swefficiency/swefficiency
Project-URL: Bug Tracker, https://github.com/swefficiency/swefficiency/issues
Project-URL: Paper, https://arxiv.org/abs/2511.06090
Keywords: nlp,benchmark,code,performance,optimization
Classifier: Programming Language :: Python :: 3.10
Classifier: Programming Language :: Python :: 3.11
Classifier: Programming Language :: Python :: 3.12
Classifier: Programming Language :: Python :: 3 :: Only
Classifier: License :: OSI Approved :: Apache Software License
Classifier: Operating System :: OS Independent
Requires-Python: >=3.8
License-File: LICENSE
Requires-Dist: beautifulsoup4
Requires-Dist: chardet
Requires-Dist: datasets
Requires-Dist: docker
Requires-Dist: fastcore
Requires-Dist: ghapi
Requires-Dist: GitPython
Requires-Dist: pandas
Requires-Dist: pre-commit
Requires-Dist: python-dotenv
Requires-Dist: requests
Requires-Dist: rich
Requires-Dist: tqdm
Requires-Dist: unidiff
Provides-Extra: inference
Requires-Dist: jedi; extra == "inference"
Requires-Dist: jinja2; extra == "inference"
Dynamic: license-file
